hanzo/arc2warc.py
hanzo/warc2warc.py
hanzo/warcdump.py
hanzo/warcextract.py
hanzo/warcfilter.py
hanzo/warcindex.py
hanzo/warclinks.py
hanzo/warcpayload.py
hanzo/warcvalid.py
hanzo/httptools/__init__.py
hanzo/httptools/messaging.py
hanzo/httptools/semantics.py
hanzo/httptools/tests/__init__.py
hanzo/httptools/tests/parse_test.py
hanzo/warctools/__init__.py
hanzo/warctools/arc.py
hanzo/warctools/archive_detect.py
hanzo/warctools/log.py
hanzo/warctools/mixed.py
hanzo/warctools/record.py
hanzo/warctools/s3.py
hanzo/warctools/stream.py
hanzo/warctools/warc.py
hanzo/warctools/tests/__init__.py
hanzo/warctools/tests/test_warctools.py
warctools-5.0.1.dist-info/licenses/LICENSE
warctools-5.0.1.dist-info/METADATA
warctools-5.0.1.dist-info/WHEEL
warctools-5.0.1.dist-info/entry_points.txt
warctools-5.0.1.dist-info/top_level.txt
warctools-5.0.1.dist-info/RECORD
