Metadata-Version: 2.4
Name: warctools
Version: 5.0.1
Summary: Command line tools and libraries for handling and manipulating WARC files (and HTTP contents)
Author-email: Thomas Figg <tef@warctools.twentygototen.org>
Maintainer-email: Internet Archive <info@archive.org>
License-Expression: MIT
Classifier: Operating System :: OS Independent
Classifier: Programming Language :: Python :: 3.5
Classifier: Topic :: System :: Archiving
Requires-Python: >=3.5
License-File: LICENSE
Dynamic: license-file
